git_pre_push_hook/__init__.py
git_pre_push_hook/engine.py
git_pre_push_hook/hook.py
git_pre_push_hook/install.py
git_pre_push_hook/linters.py
git_pre_push_hook-0.2.6.dist-info/DESCRIPTION.rst
git_pre_push_hook-0.2.6.dist-info/METADATA
git_pre_push_hook-0.2.6.dist-info/RECORD
git_pre_push_hook-0.2.6.dist-info/WHEEL
git_pre_push_hook-0.2.6.dist-info/entry_points.txt
git_pre_push_hook-0.2.6.dist-info/metadata.json
git_pre_push_hook-0.2.6.dist-info/top_level.txt
